Metadata-Version: 1.1
Name: mobilpy
Version: 0.3
Summary: Library that helps create the XML necessary for online payments with MobilPay
Home-page: https://github.com/onel/mobilpy
Author: Andrei Onel
Author-email: andrei@edumo.org
License: MIT
Keywords: online payments mobilpay netopia
Platform: UNKNOWN
Classifier: Development Status :: 4 - Beta
Classifier: License :: OSI Approved :: MIT License
Classifier: Programming Language :: Python :: 2.7
Classifier: Topic :: Office/Business :: Financial
Classifier: Topic :: Text Processing :: Markup :: XML
